SAUSERO/Color_Codes.py
SAUSERO/OsirisDRP.py
SAUSERO/__init__.py
SAUSERO/aligning_osirisplus.py
SAUSERO/astrometry_osirisplus.py
SAUSERO/check_files.py
SAUSERO/photometry_osirisplus.py
SAUSERO/reduction_osirisplus.py
SAUSERO/BPM/BPM_OSIRIS_PLUS.fits
SAUSERO/config/configuration.json
SAUSERO/config/photometric_standards.json
sausero-1.0.0.dist-info/licenses/LICENSE
sausero-1.0.0.dist-info/METADATA
sausero-1.0.0.dist-info/WHEEL
sausero-1.0.0.dist-info/entry_points.txt
sausero-1.0.0.dist-info/top_level.txt
sausero-1.0.0.dist-info/RECORD
