Metadata-Version: 2.4
Name: sausero
Version: 1.0.0
Summary: This software is designed to reduce Broad Band Imaging observations obtained with OSIRIS+.
Home-page: https://github.com/Kennicutt/SAUSERO
Author: Fabricio M. Pérez-Toledo
Author-email: fabricio.telescope@gmail.com
Classifier: Programming Language :: Python :: 3
Classifier: License :: OSI Approved :: GNU General Public License v3 (GPLv3)
Classifier: Operating System :: OS Independent
Requires-Python: >=3.9
License-File: LICENSE
Requires-Dist: astroalign
Requires-Dist: astrometry_net_client
Requires-Dist: astropy
Requires-Dist: astroquery
Requires-Dist: ccdproc
Requires-Dist: lacosmic
Requires-Dist: loguru
Requires-Dist: matplotlib
Requires-Dist: numpy
Requires-Dist: PyYAML
Requires-Dist: sep
Dynamic: author
Dynamic: author-email
Dynamic: classifier
Dynamic: description
Dynamic: description-content-type
Dynamic: home-page
Dynamic: license-file
Dynamic: requires-dist
Dynamic: requires-python
Dynamic: summary
